asydo/__init__.py
asydo/db.py
asydo/factory.py
asydo/vu.py
asydo-0.1.1.data/scripts/dbCreator.py
asydo-0.1.1.dist-info/DESCRIPTION.rst
asydo-0.1.1.dist-info/METADATA
asydo-0.1.1.dist-info/RECORD
asydo-0.1.1.dist-info/WHEEL
asydo-0.1.1.dist-info/metadata.json
asydo-0.1.1.dist-info/top_level.txt
asydo-0.1.1.dist-info/zip-safe
