Metadata-Version: 2.0
Name: asydo
Version: 0.1.1
Summary: Astronomical Syntetic Data Observations
Home-page: https://github.com/ChileanVirtualObservatory/asydo
Author: CSRG
Author-email: contact@lirae.cl
License: GPLv2
Platform: UNKNOWN
Classifier: Intended Audience :: Science/Research
Classifier: License :: OSI Approved :: GNU General Public License v2 (GPLv2)
Classifier: Topic :: Scientific/Engineering :: Astronomy
Classifier: Programming Language :: Python :: 2.7
Requires-Dist: numpy
Requires-Dist: astropy
Requires-Dist: matplotlib
Requires-Dist: urllib3
Requires-Dist: scipy (>=0.19.0)
Requires-Dist: pysqlite
